eoq3utils/__init__.py
eoq3utils/domainfactory.py
eoq3utils/cli/__init__.py
eoq3utils/cli/common.py
eoq3utils/cli/commonpyecore.py
eoq3utils/cli/commonws.py
eoq3utils/cli/domaindotcpcli.py
eoq3utils/cli/domaindowscli.py
eoq3utils/cli/ecorefiletoeoqfilecli.py
eoq3utils/cli/eoqfiletoecorefilecli.py
eoq3utils/cli/loadecorefiletcpcli.py
eoq3utils/cli/loadecorefilewscli.py
eoq3utils/cli/loadeoqfiletcpcli.py
eoq3utils/cli/loadeoqfilewscli.py
eoq3utils/cli/saveecorefiletcpcli.py
eoq3utils/cli/saveecorefilewscli.py
eoq3utils/cli/saveeoqfiletcpcli.py
eoq3utils/cli/saveeoqfilewscli.py
eoq3utils/services/__init__.py
eoq3utils/services/common.py
eoq3utils/services/wsactionhandlercli.py
eoq3utils/services/wsactionmanagercli.py
eoq3utils/services/wsdomaincli.py
eoq3utils/services/wsmplcli.py
eoq3utils/services/wsservercli.py
eoq3utils-2.10.10.dist-info/licenses/LICENSE
eoq3utils-2.10.10.dist-info/METADATA
eoq3utils-2.10.10.dist-info/WHEEL
eoq3utils-2.10.10.dist-info/top_level.txt
eoq3utils-2.10.10.dist-info/RECORD
