Metadata-Version: 2.4
Name: eoq3utils
Version: 2.10.10
Summary: Swiss Army knife package for EOQ3, e.g. domain creation and destruction, CLI tools, and services
Author-email: Bjoern Annighoefer <bjoern.annighoefer@ils.uni-stuttgart.de>
Project-URL: Homepage, https://gitlab.com/eoq/py/eoq3utils
Project-URL: Issues, https://gitlab.com/eoq/py/eoq3utils/-/issues
Classifier: Programming Language :: Python :: 3
Classifier: License :: OSI Approved :: MIT License
Classifier: Operating System :: OS Independent
Requires-Python: >=3.10
License-File: LICENSE
Requires-Dist: eoq3
Requires-Dist: eoq3conceptsgen
Requires-Dist: eoq3pyaccesscontroller
Requires-Dist: eoq3pyactions
Requires-Dist: eoq3pyecoreutils
Requires-Dist: eoq3pyecoremdb
Requires-Dist: eoq3pyecorempl
Requires-Dist: eoq3autobahnws
Requires-Dist: eoq3tcp
Requires-Dist: configargparse
Dynamic: license-file
